Metadata-Version: 1.0
Name: sapipy
Version: 0.1.1
Summary: A Python interface for the Solar Analytics API
Home-page: https://github.com/aws404/sapipy
Author: aws404
Author-email: aws40404@gmail.com
License: GNU GPLv3
Platform: UNKNOWN
